libsampled/__init__.py
libsampled/canonical.py
libsampled/sampled.py
libsampled-0.1.5.dist-info/LICENSE
libsampled-0.1.5.dist-info/METADATA
libsampled-0.1.5.dist-info/WHEEL
libsampled-0.1.5.dist-info/top_level.txt
libsampled-0.1.5.dist-info/RECORD
