Metadata-Version: 2.1
Name: libsampled
Version: 0.1.5
Summary: Collect samples/events for ingest to sampled
Home-page: https://github.com/boxidau/sampled
Author: Simon Mirco
Author-email: python@box.id.au
License: UNKNOWN
Project-URL: Bug Tracker, https://github.com/boxidau/sampled/issues
Platform: UNKNOWN
Classifier: Programming Language :: Python :: 3
Classifier: License :: OSI Approved :: MIT License
Classifier: Operating System :: OS Independent
Requires-Python: >=3.6
License-File: LICENSE
